Metadata-Version: 1.1
Name: scrapyMysql
Version: 0.1.2
Summary: make scrapy store data into mysql easier
Home-page: https://github.com/MRLGC/scrapyMysql
Author: Lgchaos
Author-email: 984684973@qq.com
License: MIT
Keywords: scrapy
Platform: UNKNOWN
Classifier: Environment :: Web Environment
Classifier: Intended Audience :: Developers
Classifier: Operating System :: OS Independent
Classifier: Topic :: Text Processing :: Indexing
Classifier: Topic :: Utilities
Classifier: Topic :: Internet
Classifier: Topic :: Software Development :: Libraries :: Python Modules
Classifier: Programming Language :: Python
Classifier: Programming Language :: Python :: 3.6
